{
  "generated": "2026-02-13T16:04:52.972319",
  "silver_price_usd": 77.05999755859375,
  "contracts": [
    {
      "month_label": "FEB 26",
      "settle_price": 75.546,
      "high": 78.47,
      "low": 74.83,
      "last": 78.345,
      "volume": 62,
      "open_interest": 218,
      "change": 2.799,
      "trade_date": "02/13/2026",
      "source": "cme_api",
      "oz_standing_for_delivery": 1090000,
      "oz_delivered_today": 0,
      "kg_standing": 33902.83881843941,
      "tonnes_standing": 33.90283881843941
    },
    {
      "month_label": "MAR 26",
      "settle_price": 75.682,
      "high": 79.265,
      "low": 73.745,
      "last": 77.175,
      "volume": 38133,
      "open_interest": 59399,
      "change": 1.493,
      "trade_date": "02/13/2026",
      "source": "cme_api",
      "oz_standing_for_delivery": 296995000,
      "oz_delivered_today": 0,
      "kg_standing": 9237590.472369187,
      "tonnes_standing": 9237.590472369187
    },
    {
      "month_label": "APR 26",
      "settle_price": 75.961,
      "high": 79.505,
      "low": 74.01,
      "last": 77.335,
      "volume": 784,
      "open_interest": 608,
      "change": 1.374,
      "trade_date": "02/13/2026",
      "source": "cme_api",
      "oz_standing_for_delivery": 3040000,
      "oz_delivered_today": 0,
      "kg_standing": 94554.706429409,
      "tonnes_standing": 94.554706429409
    },
    {
      "month_label": "MAY 26",
      "settle_price": 76.256,
      "high": 79.83,
      "low": 74.5,
      "last": 77.92,
      "volume": 10092,
      "open_interest": 42004,
      "change": 1.664,
      "trade_date": "02/13/2026",
      "source": "cme_api",
      "oz_standing_for_delivery": 210020000,
      "oz_delivered_today": 0,
      "kg_standing": 6532361.659310684,
      "tonnes_standing": 6532.3616593106835
    },
    {
      "month_label": "JUN 26",
      "settle_price": 76.558,
      "high": 79.3,
      "low": 75.79,
      "last": 78.515,
      "volume": 71,
      "open_interest": 137,
      "change": 1.957,
      "trade_date": "02/13/2026",
      "source": "cme_api",
      "oz_standing_for_delivery": 685000,
      "oz_delivered_today": 0,
      "kg_standing": 21305.912468468803,
      "tonnes_standing": 21.305912468468804
    },
    {
      "month_label": "JUL 26",
      "settle_price": 76.842,
      "high": 80.36,
      "low": 75.0,
      "last": 77.545,
      "volume": 1331,
      "open_interest": 18049,
      "change": 0.703,
      "trade_date": "02/13/2026",
      "source": "cme_api",
      "oz_standing_for_delivery": 90245000,
      "oz_delivered_today": 0,
      "kg_standing": 2806937.329513821,
      "tonnes_standing": 2806.9373295138207
    },
    {
      "month_label": "AUG 26",
      "settle_price": 77.131,
      "high": 71.5,
      "low": 65.82,
      "last": 65.82,
      "volume": 2,
      "open_interest": 65,
      "change": -11.311,
      "trade_date": "02/13/2026",
      "source": "cme_api",
      "oz_standing_for_delivery": 325000,
      "oz_delivered_today": 0,
      "kg_standing": 10108.644601828264,
      "tonnes_standing": 10.108644601828264
    },
    {
      "month_label": "SEP 26",
      "settle_price": 77.384,
      "high": 80.365,
      "low": 78.025,
      "last": 80.365,
      "volume": 512,
      "open_interest": 4631,
      "change": 2.981,
      "trade_date": "02/13/2026",
      "source": "cme_api",
      "oz_standing_for_delivery": 23155000,
      "oz_delivered_today": 0,
      "kg_standing": 720202.0484779491,
      "tonnes_standing": 720.2020484779491
    },
    {
      "month_label": "OCT 26",
      "settle_price": 77.604,
      "high": 80.57,
      "low": 77.495,
      "last": 79.615,
      "volume": 8,
      "open_interest": 25,
      "change": 2.011,
      "trade_date": "02/13/2026",
      "source": "cme_api",
      "oz_standing_for_delivery": 125000,
      "oz_delivered_today": 0,
      "kg_standing": 3887.94023147241,
      "tonnes_standing": 3.8879402314724096
    },
    {
      "month_label": "NOV 26",
      "settle_price": 77.863,
      "high": 84.64,
      "low": 84.135,
      "last": 84.135,
      "volume": 6,
      "open_interest": 33,
      "change": 6.272,
      "trade_date": "02/13/2026",
      "source": "cme_api",
      "oz_standing_for_delivery": 165000,
      "oz_delivered_today": 0,
      "kg_standing": 5132.081105543581,
      "tonnes_standing": 5.13208110554358
    },
    {
      "month_label": "DEC 26",
      "settle_price": 78.073,
      "high": 81.44,
      "low": 77.76,
      "last": 81.44,
      "volume": 408,
      "open_interest": 6559,
      "change": 3.367,
      "trade_date": "02/13/2026",
      "source": "cme_api",
      "oz_standing_for_delivery": 32795000,
      "oz_delivered_today": 0,
      "kg_standing": 1020039.9991291014,
      "tonnes_standing": 1020.0399991291014
    },
    {
      "month_label": "JAN 27",
      "settle_price": 78.305,
      "high": 79.24,
      "low": 79.24,
      "last": 79.24,
      "volume": 2,
      "open_interest": 18,
      "change": 0.935,
      "trade_date": "02/13/2026",
      "source": "cme_api",
      "oz_standing_for_delivery": 90000,
      "oz_delivered_today": 0,
      "kg_standing": 2799.3169666601348,
      "tonnes_standing": 2.7993169666601347
    },
    {
      "month_label": "FEB 27",
      "settle_price": 78.52,
      "high": 86.155,
      "low": 86.155,
      "last": 86.155,
      "volume": 3,
      "open_interest": 15,
      "change": 7.635,
      "trade_date": "02/13/2026",
      "source": "cme_api",
      "oz_standing_for_delivery": 75000,
      "oz_delivered_today": 0,
      "kg_standing": 2332.764138883446,
      "tonnes_standing": 2.3327641388834457
    },
    {
      "month_label": "MAR 27",
      "settle_price": 78.728,
      "high": 81.9,
      "low": 81.9,
      "last": 81.9,
      "volume": 42,
      "open_interest": 385,
      "change": 3.172,
      "trade_date": "02/13/2026",
      "source": "cme_api",
      "oz_standing_for_delivery": 1925000,
      "oz_delivered_today": 0,
      "kg_standing": 59874.279564675104,
      "tonnes_standing": 59.874279564675106
    },
    {
      "month_label": "APR 27",
      "settle_price": 78.939,
      "high": 106.68,
      "low": 106.67,
      "last": 106.68,
      "volume": 2,
      "open_interest": 2,
      "change": 27.741,
      "trade_date": "02/13/2026",
      "source": "cme_api",
      "oz_standing_for_delivery": 10000,
      "oz_delivered_today": 0,
      "kg_standing": 311.03521851779277,
      "tonnes_standing": 0.31103521851779276
    },
    {
      "month_label": "MAY 27",
      "settle_price": 79.166,
      "high": 76.2,
      "low": 76.2,
      "last": 76.2,
      "volume": 12,
      "open_interest": 116,
      "change": -2.966,
      "trade_date": "02/13/2026",
      "source": "cme_api",
      "oz_standing_for_delivery": 580000,
      "oz_delivered_today": 0,
      "kg_standing": 18040.04267403198,
      "tonnes_standing": 18.04004267403198
    },
    {
      "month_label": "JUN 27",
      "settle_price": 79.38,
      "high": 94.845,
      "low": 94.645,
      "last": 94.645,
      "volume": 3,
      "open_interest": 1,
      "change": 15.265,
      "trade_date": "02/13/2026",
      "source": "cme_api",
      "oz_standing_for_delivery": 5000,
      "oz_delivered_today": 0,
      "kg_standing": 155.51760925889639,
      "tonnes_standing": 0.15551760925889638
    },
    {
      "month_label": "JUL 27",
      "settle_price": 79.614,
      "high": 81.18,
      "low": 80.93,
      "last": 81.18,
      "volume": 7,
      "open_interest": 53,
      "change": 1.566,
      "trade_date": "02/13/2026",
      "source": "cme_api",
      "oz_standing_for_delivery": 265000,
      "oz_delivered_today": 0,
      "kg_standing": 8242.433290721508,
      "tonnes_standing": 8.24243329072151
    },
    {
      "month_label": "SEP 27",
      "settle_price": 80.063,
      "high": 95.41,
      "low": 95.325,
      "last": 95.325,
      "volume": 4,
      "open_interest": 16,
      "change": 15.262,
      "trade_date": "02/13/2026",
      "source": "cme_api",
      "oz_standing_for_delivery": 80000,
      "oz_delivered_today": 0,
      "kg_standing": 2488.281748142342,
      "tonnes_standing": 2.488281748142342
    },
    {
      "month_label": "DEC 27",
      "settle_price": 80.667,
      "high": 94.77,
      "low": 94.77,
      "last": 94.77,
      "volume": 4,
      "open_interest": 51,
      "change": 14.103,
      "trade_date": "02/13/2026",
      "source": "cme_api",
      "oz_standing_for_delivery": 255000,
      "oz_delivered_today": 0,
      "kg_standing": 7931.398072203716,
      "tonnes_standing": 7.931398072203716
    }
  ],
  "delivery_summary": {
    "source": "pdf",
    "business_date": "02/12/2026",
    "product": "COMEX 5000 SILVER FUTURES",
    "month_headers": [
      "PREV DEC",
      "JAN",
      "FEB",
      "MAR",
      "APR",
      "MAY",
      "JUN",
      "JUL",
      "AUG",
      "SEP",
      "OCT",
      "NOV",
      "DEC"
    ],
    "totals": {
      "PREV DEC": 12946,
      "JAN": 9889,
      "FEB": 4595
    },
    "firms": [
      {
        "firm": "FIRM NAME O I/S PREV DEC",
        "type": null,
        "values": [
          "FIRM NAME O I/S PREV DEC",
          "JAN",
          "FEB",
          "MAR",
          "APR",
          "MAY",
          "JUN",
          "JUL",
          "AUG",
          "SEP",
          "OCT",
          "NOV",
          "DEC",
          ""
        ]
      },
      {
        "firm": "GOLDMAN",
        "type": "S",
        "values": [
          "GOLDMAN",
          "C",
          "S",
          "0",
          "0",
          "0",
          "",
          "",
          "",
          "",
          "",
          "",
          "",
          "",
          "",
          "",
          ""
        ]
      },
      {
        "firm": "GOLDMAN",
        "type": "S",
        "values": [
          "GOLDMAN",
          "H",
          "S",
          "",
          "",
          "144",
          "",
          "",
          "",
          "",
          "",
          "",
          "",
          "",
          "",
          "",
          ""
        ]
      },
      {
        "firm": "DEUTSCHE BANK",
        "type": "S",
        "values": [
          "DEUTSCHE BANK",
          "C",
          "S",
          "0",
          "",
          "",
          "",
          "",
          "",
          "",
          "",
          "",
          "",
          "",
          "",
          "",
          ""
        ]
      },
      {
        "firm": "DEUTSCHE BANK AG",
        "type": "S",
        "values": [
          "DEUTSCHE BANK AG",
          "H",
          "S",
          "1455",
          "476",
          "369",
          "",
          "",
          "",
          "",
          "",
          "",
          "",
          "",
          "",
          "",
          ""
        ]
      },
      {
        "firm": "MIZUHO SECURITIES US",
        "type": "S",
        "values": [
          "MIZUHO SECURITIES US",
          "C",
          "S",
          "2",
          "255",
          "",
          "",
          "",
          "",
          "",
          "",
          "",
          "",
          "",
          "",
          "",
          ""
        ]
      },
      {
        "firm": "MACQUARIE FUTURES US",
        "type": "S",
        "values": [
          "MACQUARIE FUTURES US",
          "C",
          "S",
          "0",
          "0",
          "0",
          "",
          "",
          "",
          "",
          "",
          "",
          "",
          "",
          "",
          "",
          ""
        ]
      },
      {
        "firm": "MACQUARIE FUTURES US",
        "type": "S",
        "values": [
          "MACQUARIE FUTURES US",
          "H",
          "S",
          "188",
          "966",
          "648",
          "",
          "",
          "",
          "",
          "",
          "",
          "",
          "",
          "",
          "",
          ""
        ]
      },
      {
        "firm": "SG AMERICAS",
        "type": "S",
        "values": [
          "SG AMERICAS",
          "C",
          "S",
          "0",
          "",
          "",
          "",
          "",
          "",
          "",
          "",
          "",
          "",
          "",
          "",
          "",
          ""
        ]
      },
      {
        "firm": "SG AMERICAS",
        "type": "S",
        "values": [
          "SG AMERICAS",
          "H",
          "S",
          "",
          "",
          "2",
          "",
          "",
          "",
          "",
          "",
          "",
          "",
          "",
          "",
          "",
          ""
        ]
      },
      {
        "firm": "MAREX",
        "type": "S",
        "values": [
          "MAREX",
          "C",
          "S",
          "29",
          "",
          "",
          "",
          "",
          "",
          "",
          "",
          "",
          "",
          "",
          "",
          "",
          ""
        ]
      },
      {
        "firm": "FIRM NAME O I/S PREV DEC",
        "type": null,
        "values": [
          "FIRM NAME O I/S PREV DEC",
          "JAN",
          "FEB",
          "MAR",
          "APR",
          "MAY",
          "JUN",
          "JUL",
          "AUG",
          "SEP",
          "OCT",
          "NOV",
          "DEC",
          ""
        ]
      },
      {
        "firm": "MAREX",
        "type": "S",
        "values": [
          "MAREX",
          "H",
          "S",
          "400",
          "",
          "",
          "",
          "",
          "",
          "",
          "",
          "",
          "",
          "",
          "",
          "",
          ""
        ]
      },
      {
        "firm": "BMO CAPITAL MARKETS",
        "type": "S",
        "values": [
          "BMO CAPITAL MARKETS",
          "H",
          "S",
          "9",
          "3",
          "",
          "",
          "",
          "",
          "",
          "",
          "",
          "",
          "",
          "",
          "",
          ""
        ]
      },
      {
        "firm": "NANHUA USA-HK",
        "type": "S",
        "values": [
          "NANHUA USA-HK",
          "C",
          "S",
          "0",
          "",
          "",
          "",
          "",
          "",
          "",
          "",
          "",
          "",
          "",
          "",
          "",
          ""
        ]
      },
      {
        "firm": "HSBC",
        "type": "S",
        "values": [
          "HSBC",
          "C",
          "S",
          "335",
          "275",
          "137",
          "",
          "",
          "",
          "",
          "",
          "",
          "",
          "",
          "",
          "",
          ""
        ]
      },
      {
        "firm": "HSBC",
        "type": "S",
        "values": [
          "HSBC",
          "H",
          "S",
          "250",
          "251",
          "265",
          "",
          "",
          "",
          "",
          "",
          "",
          "",
          "",
          "",
          "",
          ""
        ]
      },
      {
        "firm": "STANDARD CHARTERED B",
        "type": "S",
        "values": [
          "STANDARD CHARTERED B",
          "H",
          "S",
          "",
          "",
          "80",
          "",
          "",
          "",
          "",
          "",
          "",
          "",
          "",
          "",
          "",
          ""
        ]
      },
      {
        "firm": "WEDBUSH SECURITIES",
        "type": "S",
        "values": [
          "WEDBUSH SECURITIES",
          "C",
          "S",
          "0",
          "0",
          "",
          "",
          "",
          "",
          "",
          "",
          "",
          "",
          "",
          "",
          "",
          ""
        ]
      },
      {
        "firm": "WELLS FARGO SECURITI",
        "type": "S",
        "values": [
          "WELLS FARGO SECURITI",
          "C",
          "S",
          "10",
          "0",
          "0",
          "",
          "",
          "",
          "",
          "",
          "",
          "",
          "",
          "",
          "",
          ""
        ]
      },
      {
        "firm": "WELLS FARGO SECURITI",
        "type": "S",
        "values": [
          "WELLS FARGO SECURITI",
          "H",
          "S",
          "125",
          "1165",
          "502",
          "",
          "",
          "",
          "",
          "",
          "",
          "",
          "",
          "",
          "",
          ""
        ]
      },
      {
        "firm": "MAREX CAPITAL MARKET",
        "type": "S",
        "values": [
          "MAREX CAPITAL MARKET",
          "C",
          "S",
          "7",
          "56",
          "",
          "",
          "",
          "",
          "",
          "",
          "",
          "",
          "",
          "",
          "",
          ""
        ]
      },
      {
        "firm": "FIRM NAME O I/S PREV DEC",
        "type": null,
        "values": [
          "FIRM NAME O I/S PREV DEC",
          "JAN",
          "FEB",
          "MAR",
          "APR",
          "MAY",
          "JUN",
          "JUL",
          "AUG",
          "SEP",
          "OCT",
          "NOV",
          "DEC",
          ""
        ]
      },
      {
        "firm": "SCOTIA CAPITAL (USA)",
        "type": "S",
        "values": [
          "SCOTIA CAPITAL (USA)",
          "H",
          "S",
          "449",
          "170",
          "223",
          "",
          "",
          "",
          "",
          "",
          "",
          "",
          "",
          "",
          "",
          ""
        ]
      },
      {
        "firm": "INTERACTIVE BROKERS",
        "type": "S",
        "values": [
          "INTERACTIVE BROKERS",
          "C",
          "S",
          "",
          "2",
          "2",
          "",
          "",
          "",
          "",
          "",
          "",
          "",
          "",
          "",
          "",
          ""
        ]
      },
      {
        "firm": "BNP PARIBAS SEC CORP",
        "type": "S",
        "values": [
          "BNP PARIBAS SEC CORP",
          "H",
          "S",
          "400",
          "",
          "",
          "",
          "",
          "",
          "",
          "",
          "",
          "",
          "",
          "",
          "",
          ""
        ]
      },
      {
        "firm": "BOFA SECURITIES",
        "type": "S",
        "values": [
          "BOFA SECURITIES",
          "H",
          "S",
          "213",
          "267",
          "85",
          "",
          "",
          "",
          "",
          "",
          "",
          "",
          "",
          "",
          "",
          ""
        ]
      },
      {
        "firm": "MORGAN STANLEY",
        "type": "S",
        "values": [
          "MORGAN STANLEY",
          "C",
          "S",
          "10",
          "4",
          "0",
          "",
          "",
          "",
          "",
          "",
          "",
          "",
          "",
          "",
          "",
          ""
        ]
      },
      {
        "firm": "MORGAN STANLEY",
        "type": "S",
        "values": [
          "MORGAN STANLEY",
          "H",
          "S",
          "",
          "496",
          "188",
          "",
          "",
          "",
          "",
          "",
          "",
          "",
          "",
          "",
          "",
          ""
        ]
      },
      {
        "firm": "JP MORGAN SECURITIES",
        "type": "S",
        "values": [
          "JP MORGAN SECURITIES",
          "C",
          "S",
          "6331",
          "2737",
          "1334",
          "",
          "",
          "",
          "",
          "",
          "",
          "",
          "",
          "",
          "",
          ""
        ]
      },
      {
        "firm": "JP MORGAN SECURITIES",
        "type": "S",
        "values": [
          "JP MORGAN SECURITIES",
          "H",
          "S",
          "137",
          "",
          "",
          "",
          "",
          "",
          "",
          "",
          "",
          "",
          "",
          "",
          "",
          ""
        ]
      },
      {
        "firm": "RJ OBRIEN",
        "type": "S",
        "values": [
          "RJ OBRIEN",
          "C",
          "S",
          "0",
          "2",
          "",
          "",
          "",
          "",
          "",
          "",
          "",
          "",
          "",
          "",
          "",
          ""
        ]
      },
      {
        "firm": "STONEX FINANCIAL INC",
        "type": "S",
        "values": [
          "STONEX FINANCIAL INC",
          "C",
          "S",
          "164",
          "244",
          "0",
          "",
          "",
          "",
          "",
          "",
          "",
          "",
          "",
          "",
          "",
          ""
        ]
      },
      {
        "firm": "FIRM NAME O I/S PREV DEC",
        "type": null,
        "values": [
          "FIRM NAME O I/S PREV DEC",
          "JAN",
          "FEB",
          "MAR",
          "APR",
          "MAY",
          "JUN",
          "JUL",
          "AUG",
          "SEP",
          "OCT",
          "NOV",
          "DEC",
          ""
        ]
      },
      {
        "firm": "STONEX FINANCIAL INC",
        "type": "S",
        "values": [
          "STONEX FINANCIAL INC",
          "H",
          "S",
          "393",
          "510",
          "482",
          "",
          "",
          "",
          "",
          "",
          "",
          "",
          "",
          "",
          "",
          ""
        ]
      },
      {
        "firm": "ABN AMRO CLR USA LLC",
        "type": "S",
        "values": [
          "ABN AMRO CLR USA LLC",
          "C",
          "S",
          "105",
          "5",
          "0",
          "",
          "",
          "",
          "",
          "",
          "",
          "",
          "",
          "",
          "",
          ""
        ]
      },
      {
        "firm": "UBS SECURITIES LLC",
        "type": "S",
        "values": [
          "UBS SECURITIES LLC",
          "C",
          "S",
          "8",
          "",
          "",
          "",
          "",
          "",
          "",
          "",
          "",
          "",
          "",
          "",
          "",
          ""
        ]
      },
      {
        "firm": "PTG DIVISION OF SGAS",
        "type": "S",
        "values": [
          "PTG DIVISION OF SGAS",
          "C",
          "S",
          "2",
          "0",
          "0",
          "",
          "",
          "",
          "",
          "",
          "",
          "",
          "",
          "",
          "",
          ""
        ]
      },
      {
        "firm": "RBC CAP MARKETS",
        "type": "S",
        "values": [
          "RBC CAP MARKETS",
          "C",
          "S",
          "158",
          "63",
          "0",
          "",
          "",
          "",
          "",
          "",
          "",
          "",
          "",
          "",
          "",
          ""
        ]
      },
      {
        "firm": "RBC CAP MARKETS",
        "type": "S",
        "values": [
          "RBC CAP MARKETS",
          "H",
          "S",
          "1271",
          "",
          "",
          "",
          "",
          "",
          "",
          "",
          "",
          "",
          "",
          "",
          "",
          ""
        ]
      },
      {
        "firm": "ADVANTAGE FUTURES",
        "type": "S",
        "values": [
          "ADVANTAGE FUTURES",
          "C",
          "S",
          "22",
          "8",
          "2",
          "",
          "",
          "",
          "",
          "",
          "",
          "",
          "",
          "",
          "",
          ""
        ]
      },
      {
        "firm": "MAREX SPEC",
        "type": "S",
        "values": [
          "MAREX SPEC",
          "C",
          "S",
          "2",
          "0",
          "0",
          "",
          "",
          "",
          "",
          "",
          "",
          "",
          "",
          "",
          "",
          ""
        ]
      },
      {
        "firm": "GOLDMAN SACHS CLEARI",
        "type": "S",
        "values": [
          "GOLDMAN SACHS CLEARI",
          "C",
          "S",
          "12",
          "",
          "",
          "",
          "",
          "",
          "",
          "",
          "",
          "",
          "",
          "",
          "",
          ""
        ]
      },
      {
        "firm": "PHILLIP CAPITAL INC",
        "type": "S",
        "values": [
          "PHILLIP CAPITAL INC",
          "C",
          "S",
          "",
          "1",
          "",
          "",
          "",
          "",
          "",
          "",
          "",
          "",
          "",
          "",
          "",
          ""
        ]
      },
      {
        "firm": "FIRM NAME O I/S PREV DEC",
        "type": null,
        "values": [
          "FIRM NAME O I/S PREV DEC",
          "JAN",
          "FEB",
          "MAR",
          "APR",
          "MAY",
          "JUN",
          "JUL",
          "AUG",
          "SEP",
          "OCT",
          "NOV",
          "DEC",
          ""
        ]
      },
      {
        "firm": "CITIGROUP",
        "type": "S",
        "values": [
          "CITIGROUP",
          "C",
          "S",
          "",
          "",
          "10",
          "",
          "",
          "",
          "",
          "",
          "",
          "",
          "",
          "",
          "",
          ""
        ]
      },
      {
        "firm": "CITIGROUP",
        "type": "S",
        "values": [
          "CITIGROUP",
          "H",
          "S",
          "0",
          "1719",
          "",
          "",
          "",
          "",
          "",
          "",
          "",
          "",
          "",
          "",
          "",
          ""
        ]
      },
      {
        "firm": "ADM",
        "type": "S",
        "values": [
          "ADM",
          "C",
          "S",
          "139",
          "131",
          "122",
          "",
          "",
          "",
          "",
          "",
          "",
          "",
          "",
          "",
          "",
          ""
        ]
      },
      {
        "firm": "IRONBEAM INC",
        "type": "S",
        "values": [
          "IRONBEAM INC",
          "H",
          "S",
          "",
          "0",
          "",
          "",
          "",
          "",
          "",
          "",
          "",
          "",
          "",
          "",
          "",
          ""
        ]
      },
      {
        "firm": "CME",
        "type": "S",
        "values": [
          "CME",
          "H",
          "S",
          "320",
          "83",
          "",
          "",
          "",
          "",
          "",
          "",
          "",
          "",
          "",
          "",
          "",
          ""
        ]
      }
    ]
  },
  "warehouse_stocks": {
    "report_date": "2/12/2026",
    "activity_date": "2/11/2026",
    "total_registered_oz": 93030184.91200002,
    "total_eligible_oz": 286202821.46299994,
    "total_combined_oz": 379233006.37499994,
    "vaults": [
      {
        "vault": "ASAHI DEPOSITORY LLC",
        "registered_prev": 23953631.592,
        "registered_today": 23953631.592,
        "eligible_prev": 2987818.038,
        "eligible_today": 2555897.608,
        "total_prev": 26941449.63,
        "total_today": 26509529.2,
        "received": 0.0,
        "withdrawn": 431920.43,
        "net_change": -431920.43
      },
      {
        "vault": "BRINK'S, INC.",
        "registered_prev": 17562594.449,
        "registered_today": 16122359.646,
        "eligible_prev": 39199825.671,
        "eligible_today": 40640060.474,
        "total_prev": 56762420.12,
        "total_today": 56762420.12,
        "received": 0.0,
        "withdrawn": 0.0,
        "net_change": 0.0
      },
      {
        "vault": "CNT DEPOSITORY, INC.",
        "registered_prev": 15343500.119,
        "registered_today": 12974598.079,
        "eligible_prev": 12937863.863,
        "eligible_today": 15306765.903,
        "total_prev": 28281363.982,
        "total_today": 28281363.982,
        "received": 0.0,
        "withdrawn": 0.0,
        "net_change": 0.0
      },
      {
        "vault": "DELAWARE DEPOSITORY",
        "registered_prev": 1966294.501,
        "registered_today": 1552701.933,
        "eligible_prev": 15977369.624,
        "eligible_today": 16261227.756,
        "total_prev": 17943664.125,
        "total_today": 17813929.689,
        "received": 0.0,
        "withdrawn": 129734.436,
        "net_change": -129734.436
      },
      {
        "vault": "HSBC BANK, USA",
        "registered_prev": 3472271.68,
        "registered_today": 3472271.68,
        "eligible_prev": 21150312.483,
        "eligible_today": 21150312.483,
        "total_prev": 24622584.163,
        "total_today": 24622584.163,
        "received": 0.0,
        "withdrawn": 0.0,
        "net_change": 0.0
      },
      {
        "vault": "INTERNATIONAL DEPOSITORY SERVICES OF DELAWARE",
        "registered_prev": 620749.47,
        "registered_today": 273789.87,
        "eligible_prev": 3295246.644,
        "eligible_today": 3642206.244,
        "total_prev": 3915996.114,
        "total_today": 3915996.114,
        "received": 0.0,
        "withdrawn": 0.0,
        "net_change": 0.0
      },
      {
        "vault": "JP MORGAN CHASE BANK NA",
        "registered_prev": 12035257.32,
        "registered_today": 12035257.32,
        "eligible_prev": 151278543.683,
        "eligible_today": 150151940.283,
        "total_prev": 163313801.003,
        "total_today": 162187197.603,
        "received": 0.0,
        "withdrawn": 1126603.4,
        "net_change": -1126603.4
      },
      {
        "vault": "LOOMIS INTERNATIONAL (US) LLC",
        "registered_prev": 7374299.767,
        "registered_today": 7374299.767,
        "eligible_prev": 23345860.186,
        "eligible_today": 23295383.436,
        "total_prev": 30720159.953,
        "total_today": 30669683.203,
        "received": 0.0,
        "withdrawn": 50476.75,
        "net_change": -50476.75
      },
      {
        "vault": "MALCA-AMIT ARMORED, INC.",
        "registered_prev": 0.0,
        "registered_today": 0,
        "eligible_prev": 0.0,
        "eligible_today": 0,
        "total_prev": 0.0,
        "total_today": 0,
        "received": 0.0,
        "withdrawn": 0.0,
        "net_change": 0.0
      },
      {
        "vault": "MALCA-AMIT USA, LLC",
        "registered_prev": 1225506.264,
        "registered_today": 1225506.264,
        "eligible_prev": 798026.177,
        "eligible_today": 798026.177,
        "total_prev": 2023532.441,
        "total_today": 2023532.441,
        "received": 0.0,
        "withdrawn": 0.0,
        "net_change": 0.0
      },
      {
        "vault": "MANFRA, TORDELLA & BROOKES, LLC",
        "registered_prev": 7038609.2,
        "registered_today": 6500477.621,
        "eligible_prev": 12226734.004,
        "eligible_today": 12167803.719,
        "total_prev": 19265343.204,
        "total_today": 18668281.34,
        "received": 0.0,
        "withdrawn": 597061.864,
        "net_change": -597061.864
      },
      {
        "vault": "STONEX PRECIOUS METALS LLC",
        "registered_prev": 7545291.14,
        "registered_today": 7545291.14,
        "eligible_prev": 233197.38,
        "eligible_today": 233197.38,
        "total_prev": 7778488.52,
        "total_today": 7778488.52,
        "received": 0.0,
        "withdrawn": 0.0,
        "net_change": 0.0
      }
    ],
    "total_registered_tonnes": 2893.566389285459,
    "total_eligible_tonnes": 8901.915711415302,
    "total_combined_tonnes": 11795.48210070076
  }
}